drmaa/__init__.py
drmaa/const.py
drmaa/errors.py
drmaa/helpers.py
drmaa/session.py
drmaa/version.py
drmaa/wrappers.py
drmaa-0.7.8.dist-info/DESCRIPTION.rst
drmaa-0.7.8.dist-info/METADATA
drmaa-0.7.8.dist-info/RECORD
drmaa-0.7.8.dist-info/WHEEL
drmaa-0.7.8.dist-info/metadata.json
drmaa-0.7.8.dist-info/top_level.txt
