Metadata-Version: 2.0
Name: drmaa
Version: 0.7.8
Summary: a python DRMAA library
Home-page: https://github.com/pygridtools/drmaa-python
Author: Dan Blanchard
Author-email: dan.blanchard@gmail.com
License: BSD
Keywords: python grid hpc drmaa
Platform: UNKNOWN
Classifier: Development Status :: 4 - Beta
Classifier: Operating System :: OS Independent
Classifier: Intended Audience :: System Administrators
Classifier: Intended Audience :: Developers
Classifier: Intended Audience :: Science/Research
Classifier: License :: OSI Approved :: BSD License
Classifier: Programming Language :: Python :: 2
Classifier: Programming Language :: Python :: 3
Classifier: Topic :: Software Development :: Libraries
Classifier: Topic :: System :: Distributed Computing
